streamlit_cognito_auth/__init__.py
streamlit_cognito_auth/auth.py
streamlit_cognito_auth/exceptions.py
streamlit_cognito_auth/session_provider.py
streamlit_cognito_auth/utils.py
streamlit_cognito_auth-1.3.0.dist-info/LICENSE
streamlit_cognito_auth-1.3.0.dist-info/METADATA
streamlit_cognito_auth-1.3.0.dist-info/WHEEL
streamlit_cognito_auth-1.3.0.dist-info/top_level.txt
streamlit_cognito_auth-1.3.0.dist-info/RECORD
