Metadata-Version: 2.1
Name: streamlit-cognito-auth
Version: 1.3.0
Summary: A Streamlit component for authenticating users with AWS Cognito
Home-page: https://github.com/pop-srw/streamlit-cognito-auth
Author: Sarawin Khemmachotikun
Author-email: khemmachotikun.s@gmail.com
Classifier: Programming Language :: Python :: 3
Classifier: License :: OSI Approved :: MIT License
Classifier: Operating System :: OS Independent
License-File: LICENSE
Requires-Dist: boto3 >=1.26.52
Requires-Dist: pycognito >=2022.12.0
Requires-Dist: pydantic <2.0.0
Requires-Dist: requests >=2.31.0
Requires-Dist: streamlit >=1.27.0
Requires-Dist: extra-streamlit-components >=0.1.56
